{"ref":{"book":"Ecclesiastes (WLC)","book_sq":"Predikuesi","chapter":5},"verses":[{"v":1,"sq":"Ki kujdes hapat e tua kur shkon te shtëpia e Perëndisë; afrohu për të dëgjuar në vend që të ofrosh flijimin e budallenjve, të cilët as nuk dinë që veprojnë keq.","src":[{"i":0,"w":"אַל","l":"408","m":"HTn","s":"H0408","t":"ʾl"},{"i":1,"w":"תְּבַהֵ֨ל","l":"926","m":"HVpj2ms","s":"H0926","t":"tbhl"},{"i":2,"w":"עַל","l":"5921 a","m":"HR","s":"H5921","t":"ʿl"},{"i":3,"w":"פִּ֜י/ךָ","l":"6310","m":"HNcmsc/Sp2ms","s":"H6310","t":"py/k"},{"i":4,"w":"וְ/לִבְּ/ךָ֧","l":"c/3820 a","m":"HC/Ncmsc/Sp2ms","s":"H3820","t":"w/lb/k"},{"i":5,"w":"אַל","l":"408","m":"HTn","s":"H0408","t":"ʾl"},{"i":6,"w":"יְמַהֵ֛ר","l":"4116 a","m":"HVpj3ms","s":"H4116","t":"ymhr"},{"i":7,"w":"לְ/הוֹצִ֥יא","l":"l/3318","m":"HR/Vhc","s":"H3318","t":"l/hwṣyʾ"},{"i":8,"w":"דָבָ֖ר","l":"1697","m":"HNcmsa","s":"H1697","t":"dbr"},{"i":9,"w":"לִ/פְנֵ֣י","l":"l/6440","m":"HR/Ncbpc","s":"H6440","t":"l/pny"},{"i":10,"w":"הָ/אֱלֹהִ֑ים","l":"d/430","m":"HTd/Ncmpa","s":"H0430","t":"h/ʾlhym"},{"i":11,"w":"כִּ֣י","l":"3588 a","m":"HC","s":"H3588","t":"ky"},{"i":12,"w":"הָ/אֱלֹהִ֤ים","l":"d/430","m":"HTd/Ncmpa","s":"H0430","t":"h/ʾlhym"},{"i":13,"w":"בַּ/שָּׁמַ֨יִם֙","l":"b/8064","m":"HRd/Ncmpa","s":"H8064","t":"b/šmym"},{"i":14,"w":"וְ/אַתָּ֣ה","l":"c/859 a","m":"HC/Pp2ms","s":"H0859","t":"w/ʾth"},{"i":15,"w":"עַל","l":"5921 a","m":"HR","s":"H5921","t":"ʿl"},{"i":16,"w":"הָ/אָ֔רֶץ","l":"d/776","m":"HTd/Ncbsa","s":"H0776","t":"h/ʾrṣ"},{"i":17,"w":"עַֽל","l":"5921 a","m":"HR","s":"H5921","t":"ʿl"},{"i":18,"w":"כֵּ֛ן","l":"3651 c","m":"HTm","s":"H3651","t":"kn"},{"i":19,"w":"יִהְי֥וּ","l":"1961","m":"HVqj3mp","s":"H1961","t":"yhyw"},{"i":20,"w":"דְבָרֶ֖י/ךָ","l":"1697","m":"HNcmpc/Sp2ms","s":"H1697","t":"dbry/k"},{"i":21,"w":"מְעַטִּֽים","l":"4592","m":"HAampa","s":"H4592","t":"mʿṭym"}],"gloss":{"H0408":"H0408 =","H0926":"H0926 =","H6310":"H6310L = a Meaning of","H3318":"H3318P = a Meaning of","H1697":"H1697O =","H6440":"H6440N = a Meaning of","H0430":"H0430I = a Part of","H8064":"H8064 =","H0776":"H0776H =","H1961":"H1961 =","H4592":"H4592 ="},"align_phrase":[]},{"v":2,"sq":"Mos u nxito me gojën tënde, dhe zemra jote të mos shpejtohet të thotë asnjë fjalë përpara Perëndisë, sepse Perëndia është në qiell dhe ti mbi tokë; prandaj fjalët e tua të jenë të pakta.","src":[{"i":0,"w":"כִּ֛י","l":"3588 a","m":"HC","s":"H3588","t":"ky"},{"i":1,"w":"בָּ֥א","l":"935","m":"HVqp3ms","s":"H0935","t":"bʾ"},{"i":2,"w":"הַ/חֲל֖וֹם","l":"d/2472","m":"HTd/Ncmsa","s":"H2472","t":"h/ḥlwm"},{"i":3,"w":"בְּ/רֹ֣ב","l":"b/7230","m":"HR/Ncbsc","s":"H7230","t":"b/rb"},{"i":4,"w":"עִנְיָ֑ן","l":"6045","m":"HNcmsa","s":"H6045","t":"ʿnyn"},{"i":5,"w":"וְ/ק֥וֹל","l":"c/6963 a","m":"HC/Ncmsc","s":"H6963","t":"w/qwl"},{"i":6,"w":"כְּסִ֖יל","l":"3684","m":"HAamsa","s":"H3684","t":"ksyl"},{"i":7,"w":"בְּ/רֹ֥ב","l":"b/7230","m":"HR/Ncbsc","s":"H7230","t":"b/rb"},{"i":8,"w":"דְּבָרִֽים","l":"1697","m":"HNcmpa","s":"H1697","t":"dbrym"}],"gloss":{"H0935":"H0935P = a Meaning of","H2472":"H2472 =","H7230":"H7230 =","H6045":"H6045 =","H3684":"H3684 =","H1697":"H1697O ="},"align_phrase":[]},{"v":3,"sq":"Sepse nga punët e shumta vijnë ëndrrat, dhe nga fjalët e shumta zëri i budallait.","src":[{"i":0,"w":"כַּ/אֲשֶׁר֩","l":"k/834 d","m":"HR/Tr","s":"H0834","t":"k/ʾšr"},{"i":1,"w":"תִּדֹּ֨ר","l":"5087","m":"HVqi2ms","s":"H5087","t":"tdr"},{"i":2,"w":"נֶ֜דֶר","l":"5088","m":"HNcmsa","s":"H5088","t":"ndr"},{"i":3,"w":"לֵֽ/אלֹהִ֗ים","l":"l/430","m":"HR/Ncmpa","s":"H0430","t":"l/ʾlhym"},{"i":4,"w":"אַל","l":"408","m":"HTn","s":"H0408","t":"ʾl"},{"i":5,"w":"תְּאַחֵר֙","l":"309","m":"HVpj2ms","s":"H0309","t":"tʾḥr"},{"i":6,"w":"לְ/שַׁלְּמ֔/וֹ","l":"l/7999 a","m":"HR/Vpc/Sp3ms","s":"H7999","t":"l/šlm/w"},{"i":7,"w":"כִּ֛י","l":"3588 a","m":"HC","s":"H3588","t":"ky"},{"i":8,"w":"אֵ֥ין","l":"369","m":"HTn","s":"H0369","t":"ʾyn"},{"i":9,"w":"חֵ֖פֶץ","l":"2656","m":"HNcmsa","s":"H2656","t":"ḥpṣ"},{"i":10,"w":"בַּ/כְּסִילִ֑ים","l":"b/3684","m":"HRd/Aampa","s":"H3684","t":"b/ksylym"},{"i":11,"w":"אֵ֥ת","l":"853","m":"HTo","s":"H0853","t":"ʾt"},{"i":12,"w":"אֲשֶׁר","l":"834 a","m":"HTr","s":"H0834","t":"ʾšr"},{"i":13,"w":"תִּדֹּ֖ר","l":"5087","m":"HVqi2ms","s":"H5087","t":"tdr"},{"i":14,"w":"שַׁלֵּֽם","l":"7999 a","m":"HVpv2ms","s":"H7999","t":"šlm"}],"gloss":{"H5087":"H5087 =","H5088":"H5088 =","H0430":"H0430I = a Part of","H0408":"H0408 =","H0309":"H0309 =","H0369":"H0369 =","H2656":"H2656 =","H3684":"H3684 =","H0853":"H0853 ="},"align_phrase":[]},{"v":4,"sq":"Kur i ke bërë një zotim Perëndisë mos humb kohë ta plotësosh, sepse ai nuk kënaqet me budallenjtë; plotëso zotimin që ke marrë.","src":[{"i":0,"w":"ט֖וֹב","l":"2896 a","m":"HAamsa","s":"H2896","t":"ṭwb"},{"i":1,"w":"אֲשֶׁ֣ר","l":"834 a","m":"HTr","s":"H0834","t":"ʾšr"},{"i":2,"w":"לֹֽא","l":"3808","m":"HTn","s":"H3808","t":"lʾ"},{"i":3,"w":"תִדֹּ֑ר","l":"5087","m":"HVqi2ms","s":"H5087","t":"tdr"},{"i":4,"w":"מִ/שֶׁ/תִּדּ֖וֹר","l":"m/s/5087","m":"HR/Tr/Vqi2ms","s":"H5087","t":"m/š/tdwr"},{"i":5,"w":"וְ/לֹ֥א","l":"c/3808","m":"HC/Tn","s":"H3808","t":"w/lʾ"},{"i":6,"w":"תְשַׁלֵּֽם","l":"7999 a","m":"HVpi2ms","s":"H7999","t":"tšlm"}],"gloss":{"H3808":"H3808 =","H5087":"H5087 ="},"align_phrase":[]},{"v":5,"sq":"Më mirë të mos marrësh zotime se sa t'i bësh dhe të mos i plotësosh.","src":[{"i":0,"w":"אַל","l":"408","m":"HTn","s":"H0408","t":"ʾl"},{"i":1,"w":"תִּתֵּ֤ן","l":"5414","m":"HVqj2ms","s":"H5414","t":"ttn"},{"i":2,"w":"אֶת","l":"853","m":"HTo","s":"H0853","t":"ʾt"},{"i":3,"w":"פִּ֨י/ךָ֙","l":"6310","m":"HNcmsc/Sp2ms","s":"H6310","t":"py/k"},{"i":4,"w":"לַ/חֲטִ֣יא","l":"l/2398","m":"HR/Vhc","s":"H2398","t":"l/ḥṭyʾ"},{"i":5,"w":"אֶת","l":"853","m":"HTo","s":"H0853","t":"ʾt"},{"i":6,"w":"בְּשָׂרֶ֔/ךָ","l":"1320","m":"HNcmsc/Sp2ms","s":"H1320","t":"bšr/k"},{"i":7,"w":"וְ/אַל","l":"c/408","m":"HC/Tn","s":"H0408","t":"w/ʾl"},{"i":8,"w":"תֹּאמַר֙","l":"559","m":"HVqj2ms","s":"H0559","t":"tʾmr"},{"i":9,"w":"לִ/פְנֵ֣י","l":"l/6440","m":"HR/Ncbpc","s":"H6440","t":"l/pny"},{"i":10,"w":"הַ/מַּלְאָ֔ךְ","l":"d/4397","m":"HTd/Ncmsa","s":"H4397","t":"h/mlʾk"},{"i":11,"w":"כִּ֥י","l":"3588 a","m":"HC","s":"H3588","t":"ky"},{"i":12,"w":"שְׁגָגָ֖ה","l":"7684","m":"HNcfsa","s":"H7684","t":"šggh"},{"i":13,"w":"הִ֑יא","l":"1931","m":"HPp3fs","s":"H1931","t":"hyʾ"},{"i":14,"w":"לָ֣/מָּה","l":"l/4100","m":"HR/Ti","s":"H4100","t":"l/mh"},{"i":15,"w":"יִקְצֹ֤ף","l":"7107","m":"HVqi3ms","s":"H7107","t":"yqṣp"},{"i":16,"w":"הָֽ/אֱלֹהִים֙","l":"d/430","m":"HTd/Ncmpa","s":"H0430","t":"h/ʾlhym"},{"i":17,"w":"עַל","l":"5921 a","m":"HR","s":"H5921","t":"ʿl"},{"i":18,"w":"קוֹלֶ֔/ךָ","l":"6963 a","m":"HNcmsc/Sp2ms","s":"H6963","t":"qwl/k"},{"i":19,"w":"וְ/חִבֵּ֖ל","l":"c/2254 b","m":"HC/Vpq3ms","s":"H2254","t":"w/ḥbl"},{"i":20,"w":"אֶת","l":"853","m":"HTo","s":"H0853","t":"ʾt"},{"i":21,"w":"מַעֲשֵׂ֥ה","l":"4639","m":"HNcmsc","s":"H4639","t":"mʿšh"},{"i":22,"w":"יָדֶֽי/ךָ","l":"3027","m":"HNcbdc/Sp2ms","s":"H3027","t":"ydy/k"}],"gloss":{"H0408":"H0408 =","H5414":"H5414Q = a Meaning of","H0853":"H0853 =","H6310":"H6310L = a Meaning of","H2398":"H2398 =","H1320":"H1320 =","H0559":"H0559 =","H6440":"H6440N = a Meaning of","H4397":"H4397H = a Meaning of","H7684":"H7684 =","H1931":"H1931 =","H4100":"H4100 =","H7107":"H7107 =","H0430":"H0430I = a Part of","H4639":"H4639K = a Meaning of","H3027":"H3027X = a Meaning of"},"align_phrase":[]},{"v":6,"sq":"Mos lejo që goja jote ta çojë trupin tënd të mëkatojë dhe mos thuaj para lajmëtarit të Perëndisë: \\\"Ka qenë gabim\\\". Pse Perëndia duhet të zemërohej me fjalët e tua dhe të shkatërronte veprën e duarve të tua?","src":[{"i":0,"w":"כִּ֣י","l":"3588 a","m":"HC","s":"H3588","t":"ky"},{"i":1,"w":"בְ/רֹ֤ב","l":"b/7230","m":"HR/Ncbsc","s":"H7230","t":"b/rb"},{"i":2,"w":"חֲלֹמוֹת֙","l":"2472","m":"HNcmpa","s":"H2472","t":"ḥlmwt"},{"i":3,"w":"וַ/הֲבָלִ֔ים","l":"c/1892","m":"HC/Ncmpa","s":"H1892","t":"w/hblym"},{"i":4,"w":"וּ/דְבָרִ֖ים","l":"c/1697","m":"HC/Ncmpa","s":"H1697","t":"w/dbrym"},{"i":5,"w":"הַרְבֵּ֑ה","l":"7235 a","m":"HVha","s":"H7235","t":"hrbh"},{"i":6,"w":"כִּ֥י","l":"3588 a","m":"HC","s":"H3588","t":"ky"},{"i":7,"w":"אֶת","l":"853","m":"HTo","s":"H0853","t":"ʾt"},{"i":8,"w":"הָ/אֱלֹהִ֖ים","l":"d/430","m":"HTd/Ncmpa","s":"H0430","t":"h/ʾlhym"},{"i":9,"w":"יְרָֽא","l":"3372","m":"HVqv2ms","s":"H3372","t":"yrʾ"}],"gloss":{"H7230":"H7230 =","H2472":"H2472 =","H1892":"H1892 =","H1697":"H1697O =","H0853":"H0853 =","H0430":"H0430I = a Part of","H3372":"H3372H = a Meaning of"},"align_phrase":[]},{"v":7,"sq":"Sepse në ëndrrat e shumta dhe në fjalët e shumta ka kotësi; por ti ke frikë nga Perëndia.","src":[{"i":0,"w":"אִם","l":"518 a","m":"HC","s":"H0518","t":"ʾm"},{"i":1,"w":"עֹ֣שֶׁק","l":"6233","m":"HNcmsc","s":"H6233","t":"ʿšq"},{"i":2,"w":"רָ֠שׁ","l":"7326","m":"HVqrmsa","s":"H7326","t":"rš"},{"i":3,"w":"וְ/גֵ֨זֶל","l":"c/1499","m":"HC/Ncmsc","s":"H1499","t":"w/gzl"},{"i":4,"w":"מִשְׁפָּ֤ט","l":"4941","m":"HNcmsa","s":"H4941","t":"mšpṭ"},{"i":5,"w":"וָ/צֶ֨דֶק֙","l":"c/6664","m":"HC/Ncmsa","s":"H6664","t":"w/ṣdq"},{"i":6,"w":"תִּרְאֶ֣ה","l":"7200","m":"HVqi2ms","s":"H7200","t":"trʾh"},{"i":7,"w":"בַ/מְּדִינָ֔ה","l":"b/4082","m":"HRd/Ncfsa","s":"H4082","t":"b/mdynh"},{"i":8,"w":"אַל","l":"408","m":"HTn","s":"H0408","t":"ʾl"},{"i":9,"w":"תִּתְמַ֖הּ","l":"8539","m":"HVqj2ms","s":"H8539","t":"ttmh"},{"i":10,"w":"עַל","l":"5921 a","m":"HR","s":"H5921","t":"ʿl"},{"i":11,"w":"הַ/חֵ֑פֶץ","l":"d/2656","m":"HTd/Ncmsa","s":"H2656","t":"h/ḥpṣ"},{"i":12,"w":"כִּ֣י","l":"3588 a","m":"HC","s":"H3588","t":"ky"},{"i":13,"w":"גָבֹ֜הַּ","l":"1364","m":"HAamsa","s":"H1364","t":"gbh"},{"i":14,"w":"מֵ/עַ֤ל","l":"m/5921 a","m":"HR/R","s":"H5921","t":"m/ʿl"},{"i":15,"w":"גָּבֹ֨הַ֙","l":"1364","m":"HAamsa","s":"H1364","t":"gbh"},{"i":16,"w":"שֹׁמֵ֔ר","l":"8104","m":"HVqrmsa","s":"H8104","t":"šmr"},{"i":17,"w":"וּ/גְבֹהִ֖ים","l":"c/1364","m":"HC/Aampa","s":"H1364","t":"w/gbhym"},{"i":18,"w":"עֲלֵי/הֶֽם","l":"5921 a","m":"HR/Sp3mp","s":"H5921","t":"ʿly/hm"}],"gloss":{"H6233":"H6233 =","H7326":"H7326 =","H1499":"H1499 = a Spelling of","H4941":"H4941K = a Part of","H6664":"H6664H = a Name of","H7200":"H7200N = a Name of","H4082":"H4082 =","H0408":"H0408 =","H8539":"H8539 =","H2656":"H2656 =","H1364":"H1364 =","H8104":"H8104J = a Meaning of"},"align_phrase":[]},{"v":8,"sq":"Në rast se në provincë sheh shtypjen e të varfërit dhe shkeljen me dhunë të së drejtës dhe të drejtësisë, mos u habit nga kjo gjë; sepse mbi një pushtet të lartë ndodhet një më i lartë dhe mbi ta disa pushtete akoma më të larta.","src":[{"i":0,"w":"וְ/יִתְר֥וֹן","l":"c/3504","m":"HC/Ncmsc","s":"H3504","t":"w/ytrwn"},{"i":1,"w":"אֶ֖רֶץ","l":"776","m":"HNcbsa","s":"H0776","t":"ʾrṣ"},{"i":2,"w":"בַּ/כֹּ֣ל","l":"b/3605","m":"HRd/Ncmsa","s":"H3605","t":"b/kl"},{"i":3,"w":"היא","l":"1931","m":"HPp3fs","s":"H1931","t":"hyʾ"},{"i":4,"w":"ה֑וּא","l":"1931","m":"HPp3ms","s":"H1931","t":"hwʾ"},{"i":5,"w":"מֶ֥לֶךְ","l":"4428","m":"HNcmsa","s":"H4428","t":"mlk"},{"i":6,"w":"לְ/שָׂדֶ֖ה","l":"l/7704 b","m":"HR/Ncmsa","s":"H7704","t":"l/šdh"},{"i":7,"w":"נֶעֱבָֽד","l":"5647","m":"HVNp3ms","s":"H5647","t":"nʿbd"}],"gloss":{"H3504":"H3504 =","H0776":"H0776H =","H3605":"H3605 =","H1931":"H1931 =","H4428":"H4428L =","H5647":"H5647J = a Meaning of"},"align_phrase":[]},{"v":9,"sq":"Toka ofron përfitime më të mëdha se çdo gjë tjetër, dhe vetë mbreti shërbehet nga fusha.","src":[{"i":0,"w":"אֹהֵ֥ב","l":"157","m":"HVqrmsa","s":"H0157","t":"ʾhb"},{"i":1,"w":"כֶּ֨סֶף֙","l":"3701","m":"HNcmsa","s":"H3701","t":"ksp"},{"i":2,"w":"לֹא","l":"3808","m":"HTn","s":"H3808","t":"lʾ"},{"i":3,"w":"יִשְׂבַּ֣ע","l":"7646","m":"HVqi3ms","s":"H7646","t":"yšbʿ"},{"i":4,"w":"כֶּ֔סֶף","l":"3701","m":"HNcmsa","s":"H3701","t":"ksp"},{"i":5,"w":"וּ/מִֽי","l":"c/4310","m":"HC/Ti","s":"H4310","t":"w/my"},{"i":6,"w":"אֹהֵ֥ב","l":"157","m":"HVqrmsa","s":"H0157","t":"ʾhb"},{"i":7,"w":"בֶּ/הָמ֖וֹן","l":"b/1995 a","m":"HRd/Ncmsa","s":"H1995","t":"b/hmwn"},{"i":8,"w":"לֹ֣א","l":"3808","m":"HTn","s":"H3808","t":"lʾ"},{"i":9,"w":"תְבוּאָ֑ה","l":"8393","m":"HNcfsa","s":"H8393","t":"tbwʾh"},{"i":10,"w":"גַּם","l":"1571","m":"HTa","s":"H1571","t":"gm"},{"i":11,"w":"זֶ֖ה","l":"2088","m":"HPdxms","s":"H2088","t":"zh"},{"i":12,"w":"הָֽבֶל","l":"1892","m":"HNcmsa","s":"H1892","t":"hbl"}],"gloss":{"H0157":"H0157H = a Meaning of","H3701":"H3701H = a Meaning of","H3808":"H3808 =","H7646":"H7646 =","H4310":"H4310 =","H8393":"H8393 =","H1571":"H1571 =","H2088":"H2088 =","H1892":"H1892 ="},"align_phrase":[]},{"v":10,"sq":"Kush është i dhënë pas parasë, nuk ngopet kurrë me para, dhe kush dëshiron pasuritë nxjerr përfitim prej tyre. Edhe kjo është kotësi.","src":[{"i":0,"w":"בִּ/רְבוֹת֙","l":"b/7235 a","m":"HR/Vqc","s":"H7235","t":"b/rbwt"},{"i":1,"w":"הַ/טּוֹבָ֔ה","l":"d/2896 c","m":"HTd/Aafsa","s":"H2896","t":"h/ṭwbh"},{"i":2,"w":"רַבּ֖וּ","l":"7235 a","m":"HVqp3cp","s":"H7235","t":"rbw"},{"i":3,"w":"אוֹכְלֶ֑י/הָ","l":"398","m":"HVqrmpc/Sp3fs","s":"H0398","t":"ʾwkly/h"},{"i":4,"w":"וּ/מַה","l":"c/4100","m":"HC/Ti","s":"H4100","t":"w/mh"},{"i":5,"w":"כִּשְׁרוֹן֙","l":"3788","m":"HNcmsa","s":"H3788","t":"kšrwn"},{"i":6,"w":"לִ/בְעָלֶ֔י/הָ","l":"l/1167","m":"HR/Ncmpc/Sp3fs","s":"H1167","t":"l/bʿly/h"},{"i":7,"w":"כִּ֖י","l":"3588 b","m":"HC","s":"H3588","t":"ky"},{"i":8,"w":"אִם","l":"518 b","m":"HC","s":"H0518","t":"ʾm"},{"i":9,"w":"ראית","l":"7212","m":"HNcmsc","s":"H7212","t":"rʾyt"},{"i":10,"w":"רְא֥וּת","l":"7207","m":"HNcfsc","s":"H7207","t":"rʾwt"},{"i":11,"w":"עֵינָֽי/ו","l":"5869 a","m":"HNcbdc/Sp3ms","s":"H5869","t":"ʿyny/w"}],"gloss":{"H0398":"H0398 =","H4100":"H4100 =","H3788":"H3788 =","H1167":"H1167K = a Meaning of","H7212":"H7212 =","H7207":"H7207 ="},"align_phrase":[]},{"v":11,"sq":"Kur rritet pasuria, shtohen edhe ata që e përpijnë; dhe çfarë përfitimi kanë prej saj pronarët, veç asaj që e shohin me sytë e tyre?","src":[{"i":0,"w":"מְתוּקָה֙","l":"4966","m":"HAafsa","s":"H4966","t":"mtwqh"},{"i":1,"w":"שְׁנַ֣ת","l":"8142","m":"HNcfsc","s":"H8142","t":"šnt"},{"i":2,"w":"הָ/עֹבֵ֔ד","l":"d/5647","m":"HTd/Vqrmsa","s":"H5647","t":"h/ʿbd"},{"i":3,"w":"אִם","l":"518 a","m":"HC","s":"H0518","t":"ʾm"},{"i":4,"w":"מְעַ֥ט","l":"4592","m":"HNcmsa","s":"H4592","t":"mʿṭ"},{"i":5,"w":"וְ/אִם","l":"c/518 a","m":"HC/C","s":"H0518","t":"w/ʾm"},{"i":6,"w":"הַרְבֵּ֖ה","l":"7235 a","m":"HVha","s":"H7235","t":"hrbh"},{"i":7,"w":"יֹאכֵ֑ל","l":"398","m":"HVqi3ms","s":"H0398","t":"yʾkl"},{"i":8,"w":"וְ/הַ/שָּׂבָע֙","l":"c/d/7647","m":"HC/Td/Ncmsa","s":"H7647","t":"w/h/šbʿ"},{"i":9,"w":"לֶֽ/עָשִׁ֔יר","l":"l/6223","m":"HRd/Aamsa","s":"H6223","t":"l/ʿšyr"},{"i":10,"w":"אֵינֶ֛/נּוּ","l":"369","m":"HTn/Sp3ms","s":"H0369","t":"ʾyn/nw"},{"i":11,"w":"מַנִּ֥יחַֽ","l":"3240","m":"HVhrmsa","s":"H3240","t":"mnyḥ"},{"i":12,"w":"ל֖/וֹ","l":"l","m":"HR/Sp3ms","s":"","t":"l/w"},{"i":13,"w":"לִ/ישֽׁוֹן","l":"l/3462","m":"HR/Vqc","s":"H3462","t":"l/yšwn"}],"gloss":{"H4966":"H4966 =","H8142":"H8142 =","H5647":"H5647J = a Meaning of","H4592":"H4592 =","H0398":"H0398 =","H7647":"H7647 =","H6223":"H6223 =","H0369":"H0369 =","H3240":"H3240 = a form of","H3462":"H3462 ="},"align_phrase":[]},{"v":12,"sq":"I ëmbël është gjumi i punonjësit, qoftë edhe kur ha pak ose shumë; por velitja e të pasurit nuk e lë atë të flerë.","src":[{"i":0,"w":"יֵ֚שׁ","l":"3426","m":"HTm","s":"H3426","t":"yš"},{"i":1,"w":"רָעָ֣ה","l":"7451 c","m":"HNcfsa","s":"H7451","t":"rʿh"},{"i":2,"w":"חוֹלָ֔ה","l":"2470 a","m":"HVqrfsa","s":"H2470","t":"ḥwlh"},{"i":3,"w":"רָאִ֖יתִי","l":"7200","m":"HVqp1cs","s":"H7200","t":"rʾyty"},{"i":4,"w":"תַּ֣חַת","l":"8478","m":"HR","s":"H8478","t":"tḥt"},{"i":5,"w":"הַ/שָּׁ֑מֶשׁ","l":"d/8121","m":"HTd/Ncbsa","s":"H8121","t":"h/šmš"},{"i":6,"w":"עֹ֛שֶׁר","l":"6239","m":"HNcmsa","s":"H6239","t":"ʿšr"},{"i":7,"w":"שָׁמ֥וּר","l":"8104","m":"HVqsmsa","s":"H8104","t":"šmwr"},{"i":8,"w":"לִ/בְעָלָ֖י/ו","l":"l/1167","m":"HR/Ncmpc/Sp3ms","s":"H1167","t":"l/bʿly/w"},{"i":9,"w":"לְ/רָעָתֽ/וֹ","l":"l/7451 c","m":"HR/Ncfsc/Sp3ms","s":"H7451","t":"l/rʿt/w"}],"gloss":{"H3426":"H3426 =","H7200":"H7200N = a Name of","H8478":"H8478L = a Meaning of","H8121":"H8121 =","H6239":"H6239 =","H8104":"H8104J = a Meaning of","H1167":"H1167K = a Meaning of"},"align_phrase":[]},{"v":13,"sq":"Éshtë një e keqe tjetër e vajtueshme që kam parë nën diell: pasuritë e ruajtura për pronarin e tyre në dëm të tij.","src":[{"i":0,"w":"וְ/אָבַ֛ד","l":"c/6","m":"HC/Vqp3ms","s":"H0006","t":"w/ʾbd"},{"i":1,"w":"הָ/עֹ֥שֶׁר","l":"d/6239","m":"HTd/Ncmsa","s":"H6239","t":"h/ʿšr"},{"i":2,"w":"הַ/ה֖וּא","l":"d/1931","m":"HTd/Pp3ms","s":"H1931","t":"h/hwʾ"},{"i":3,"w":"בְּ/עִנְיַ֣ן","l":"b/6045","m":"HR/Ncmsa","s":"H6045","t":"b/ʿnyn"},{"i":4,"w":"רָ֑ע","l":"7451 a","m":"HAamsa","s":"H7451","t":"rʿ"},{"i":5,"w":"וְ/הוֹלִ֣יד","l":"c/3205","m":"HC/Vhp3ms","s":"H3205","t":"w/hwlyd"},{"i":6,"w":"בֵּ֔ן","l":"1121 a","m":"HNcmsa","s":"H1121","t":"bn"},{"i":7,"w":"וְ/אֵ֥ין","l":"c/369","m":"HC/Tn","s":"H0369","t":"w/ʾyn"},{"i":8,"w":"בְּ/יָד֖/וֹ","l":"b/3027","m":"HR/Ncbsc/Sp3ms","s":"H3027","t":"b/yd/w"},{"i":9,"w":"מְאֽוּמָה","l":"3972","m":"HNcfsa","s":"H3972","t":"mʾwmh"}],"gloss":{"H0006":"H0006 =","H6239":"H6239 =","H1931":"H1931 =","H6045":"H6045 =","H3205":"H3205 =","H0369":"H0369 =","H3027":"H3027X = a Meaning of","H3972":"H3972 ="},"align_phrase":[]},{"v":14,"sq":"Këto pasuri humbasin për shkak të një pune të keqe, dhe kështu në duart e birit që ka lindur nuk mbetet më asgjë.","src":[{"i":0,"w":"כַּ/אֲשֶׁ֤ר","l":"k/834 d","m":"HR/Tr","s":"H0834","t":"k/ʾšr"},{"i":1,"w":"יָצָא֙","l":"3318","m":"HVqp3ms","s":"H3318","t":"yṣʾ"},{"i":2,"w":"מִ/בֶּ֣טֶן","l":"m/990","m":"HR/Ncfsc","s":"H0990","t":"m/bṭn"},{"i":3,"w":"אִמּ֔/וֹ","l":"517","m":"HNcfsc/Sp3ms","s":"H0517","t":"ʾm/w"},{"i":4,"w":"עָר֛וֹם","l":"6174","m":"HAamsa","s":"H6174","t":"ʿrwm"},{"i":5,"w":"יָשׁ֥וּב","l":"7725","m":"HVqi3ms","s":"H7725","t":"yšwb"},{"i":6,"w":"לָ/לֶ֖כֶת","l":"l/3212","m":"HR/Vqc","s":"H3212","t":"l/lkt"},{"i":7,"w":"כְּ/שֶׁ/בָּ֑א","l":"k/s/935","m":"HR/Tr/Vqp3ms","s":"H0935","t":"k/š/bʾ"},{"i":8,"w":"וּ/מְא֨וּמָה֙","l":"c/3972","m":"HC/Ncfsa","s":"H3972","t":"w/mʾwmh"},{"i":9,"w":"לֹא","l":"3808","m":"HTn","s":"H3808","t":"lʾ"},{"i":10,"w":"יִשָּׂ֣א","l":"5375","m":"HVqi3ms","s":"H5375","t":"yšʾ"},{"i":11,"w":"בַ/עֲמָל֔/וֹ","l":"b/5999","m":"HR/Ncbsc/Sp3ms","s":"H5999","t":"b/ʿml/w"},{"i":12,"w":"שֶׁ/יֹּלֵ֖ךְ","l":"s/3212","m":"HTr/Vhi3ms","s":"H3212","t":"š/ylk"},{"i":13,"w":"בְּ/יָדֽ/וֹ","l":"b/3027","m":"HR/Ncbsc/Sp3ms","s":"H3027","t":"b/yd/w"}],"gloss":{"H3318":"H3318P = a Meaning of","H0990":"H0990J = a Meaning of","H0517":"H0517 =","H6174":"H6174 =","H7725":"H7725O = a Meaning of","H3212":"H3212 = a Spelling of","H0935":"H0935P = a Meaning of","H3972":"H3972 =","H3808":"H3808 =","H5375":"H5375X = a Meaning of","H5999":"H5999 =","H3027":"H3027X = a Meaning of"},"align_phrase":[]},{"v":15,"sq":"Ashtu si ka dalë nga barku i nënës, kështu lakuriq do të kthehet për të shkuar si pati ardhur, pa marrë gjë nga mundi i tij që mund ta marrë me vete.","src":[{"i":0,"w":"וְ/גַם","l":"c/1571","m":"HC/Ta","s":"H1571","t":"w/gm"},{"i":1,"w":"זֹה֙","l":"2090","m":"HPdxms","s":"H2090","t":"zh"},{"i":2,"w":"רָעָ֣ה","l":"7451 c","m":"HNcfsa","s":"H7451","t":"rʿh"},{"i":3,"w":"חוֹלָ֔ה","l":"2470 a","m":"HVqrfsa","s":"H2470","t":"ḥwlh"},{"i":4,"w":"כָּ/ל","l":"k/3605","m":"HR/R","s":"H3605","t":"k/l"},{"i":5,"w":"עֻמַּ֥ת","l":"5980","m":"HNcfsc","s":"H5980","t":"ʿmt"},{"i":6,"w":"שֶׁ/בָּ֖א","l":"s/935","m":"HTr/Vqp3ms","s":"H0935","t":"š/bʾ"},{"i":7,"w":"כֵּ֣ן","l":"3651 c","m":"HTm","s":"H3651","t":"kn"},{"i":8,"w":"יֵלֵ֑ךְ","l":"3212","m":"HVqi3ms","s":"H3212","t":"ylk"},{"i":9,"w":"וּ/מַה","l":"c/4100","m":"HC/Ti","s":"H4100","t":"w/mh"},{"i":10,"w":"יִּתְר֣וֹן","l":"3504","m":"HNcmsa","s":"H3504","t":"ytrwn"},{"i":11,"w":"ל֔/וֹ","l":"l","m":"HR/Sp3ms","s":"","t":"l/w"},{"i":12,"w":"שֶֽׁ/יַּעֲמֹ֖ל","l":"s/5998","m":"HTr/Vqi3ms","s":"H5998","t":"š/yʿml"},{"i":13,"w":"לָ/רֽוּחַ","l":"l/7307","m":"HRd/Ncbsa","s":"H7307","t":"l/rwḥ"}],"gloss":{"H1571":"H1571 =","H2090":"H2090 =","H3605":"H3605 =","H5980":"H5980 =","H0935":"H0935P = a Meaning of","H3212":"H3212 = a Spelling of","H4100":"H4100 =","H3504":"H3504 =","H5998":"H5998 =","H7307":"H7307J = a Meaning of"},"align_phrase":[]},{"v":16,"sq":"Edhe kjo është një e keqe e vajtueshme që duhet të shkojë pikërisht ashtu si ka ardhur; dhe çfarë përfitimi ka se është munduar për erën?","src":[{"i":0,"w":"גַּ֥ם","l":"1571","m":"HTa","s":"H1571","t":"gm"},{"i":1,"w":"כָּל","l":"3605","m":"HNcmsc","s":"H3605","t":"kl"},{"i":2,"w":"יָמָ֖י/ו","l":"3117","m":"HNcmpc/Sp3ms","s":"H3117","t":"ymy/w"},{"i":3,"w":"בַּ/חֹ֣שֶׁךְ","l":"b/2822","m":"HRd/Ncmsa","s":"H2822","t":"b/ḥšk"},{"i":4,"w":"יֹאכֵ֑ל","l":"398","m":"HVqi3ms","s":"H0398","t":"yʾkl"},{"i":5,"w":"וְ/כָעַ֥ס","l":"c/3707","m":"HC/Vqq3ms","s":"H3707","t":"w/kʿs"},{"i":6,"w":"הַרְבֵּ֖ה","l":"7235 a","m":"HVha","s":"H7235","t":"hrbh"},{"i":7,"w":"וְ/חָלְי֥/וֹ","l":"c/2483","m":"HC/Ncmsc/Sp3ms","s":"H2483","t":"w/ḥly/w"},{"i":8,"w":"וָ/קָֽצֶף","l":"c/7110 a","m":"HC/Ncmsa","s":"H7110","t":"w/qṣp"}],"gloss":{"H1571":"H1571 =","H3605":"H3605 =","H3117":"H3117L = a Meaning of","H2822":"H2822 =","H0398":"H0398 =","H3707":"H3707 =","H2483":"H2483 ="},"align_phrase":[]},{"v":17,"sq":"Përveç kësaj ai ha çdo ditë të jetës së tij në errësirrë, dhe ka shumë hidhërime, sëmundje dhe telashe.","src":[{"i":0,"w":"הִנֵּ֞ה","l":"2009","m":"HTm","s":"H2009","t":"hnh"},{"i":1,"w":"אֲשֶׁר","l":"834 a","m":"HTr","s":"H0834","t":"ʾšr"},{"i":2,"w":"רָאִ֣יתִי","l":"7200","m":"HVqp1cs","s":"H7200","t":"rʾyty"},{"i":3,"w":"אָ֗נִי","l":"589","m":"HPp1cs","s":"H0589","t":"ʾny"},{"i":4,"w":"ט֣וֹב","l":"2896 a","m":"HAamsa","s":"H2896","t":"ṭwb"},{"i":5,"w":"אֲשֶׁר","l":"834 a","m":"HTr","s":"H0834","t":"ʾšr"},{"i":6,"w":"יָפֶ֣ה","l":"3303","m":"HAamsa","s":"H3303","t":"yph"},{"i":7,"w":"לֶֽ/אֶכוֹל","l":"l/398","m":"HR/Vqc","s":"H0398","t":"l/ʾkwl"},{"i":8,"w":"וְ֠/לִ/שְׁתּוֹת","l":"c/l/8354","m":"HC/R/Vqc","s":"H8354","t":"w/l/štwt"},{"i":9,"w":"וְ/לִ/רְא֨וֹת","l":"c/l/7200","m":"HC/R/Vqc","s":"H7200","t":"w/l/rʾwt"},{"i":10,"w":"טוֹבָ֜ה","l":"2896 c","m":"HAafsa","s":"H2896","t":"ṭwbh"},{"i":11,"w":"בְּ/כָל","l":"b/3605","m":"HR/Ncmsc","s":"H3605","t":"b/kl"},{"i":12,"w":"עֲמָל֣/וֹ","l":"5999","m":"HNcbsc/Sp3ms","s":"H5999","t":"ʿml/w"},{"i":13,"w":"שֶׁ/יַּעֲמֹ֣ל","l":"s/5998","m":"HTr/Vqi3ms","s":"H5998","t":"š/yʿml"},{"i":14,"w":"תַּֽחַת","l":"8478","m":"HR","s":"H8478","t":"tḥt"},{"i":15,"w":"הַ/שֶּׁ֗מֶשׁ","l":"d/8121","m":"HTd/Ncbsa","s":"H8121","t":"h/šmš"},{"i":16,"w":"מִסְפַּ֧ר","l":"4557","m":"HNcmsc","s":"H4557","t":"mspr"},{"i":17,"w":"יְמֵי","l":"3117","m":"HNcmpc","s":"H3117","t":"ymy"},{"i":18,"w":"חי/ו","l":"2416 e","m":"HNcmpc/Sp3ms","s":"H2416","t":"ḥy/w"},{"i":19,"w":"חַיָּ֛י/ו","l":"2416 e","m":"HNcmpc/Sp3ms","s":"H2416","t":"ḥyy/w"},{"i":20,"w":"אֲשֶׁר","l":"834 a","m":"HTr","s":"H0834","t":"ʾšr"},{"i":21,"w":"נָֽתַן","l":"5414","m":"HVqp3ms","s":"H5414","t":"ntn"},{"i":22,"w":"ל֥/וֹ","l":"l","m":"HR/Sp3ms","s":"","t":"l/w"},{"i":23,"w":"הָ/אֱלֹהִ֖ים","l":"d/430","m":"HTd/Ncmpa","s":"H0430","t":"h/ʾlhym"},{"i":24,"w":"כִּי","l":"3588 a","m":"HC","s":"H3588","t":"ky"},{"i":25,"w":"ה֥וּא","l":"1931","m":"HPp3ms","s":"H1931","t":"hwʾ"},{"i":26,"w":"חֶלְקֽ/וֹ","l":"2506 a","m":"HNcmsc/Sp3ms","s":"H2506","t":"ḥlq/w"}],"gloss":{"H2009":"H2009 =","H7200":"H7200N = a Name of","H0589":"H0589 =","H3303":"H3303 =","H0398":"H0398 =","H8354":"H8354 =","H3605":"H3605 =","H5999":"H5999 =","H5998":"H5998 =","H8478":"H8478L = a Meaning of","H8121":"H8121 =","H4557":"H4557 =","H3117":"H3117L = a Meaning of","H5414":"H5414Q = a Meaning of","H0430":"H0430I = a Part of","H1931":"H1931 ="},"align_phrase":[]},{"v":18,"sq":"Ja çfarë kuptova: është mirë dhe e përshtatshme për njeriun të hajë, të pijë dhe të gëzojë të mirën e gjithë mundit të tij nën diell, tërë ditët e jetës që Perëndia i jep, sepse kjo është pjesa e tij.","src":[{"i":0,"w":"גַּ֣ם","l":"1571","m":"HTa","s":"H1571","t":"gm"},{"i":1,"w":"כָּֽל","l":"3605","m":"HNcmsc","s":"H3605","t":"kl"},{"i":2,"w":"הָ/אָדָ֡ם","l":"d/120","m":"HTd/Ncmsa","s":"H0120","t":"h/ʾdm"},{"i":3,"w":"אֲשֶׁ֣ר","l":"834 a","m":"HTr","s":"H0834","t":"ʾšr"},{"i":4,"w":"נָֽתַן","l":"5414","m":"HVqp3ms","s":"H5414","t":"ntn"},{"i":5,"w":"ל֣/וֹ","l":"l","m":"HR/Sp3ms","s":"","t":"l/w"},{"i":6,"w":"הָ/אֱלֹהִים֩","l":"d/430","m":"HTd/Ncmpa","s":"H0430","t":"h/ʾlhym"},{"i":7,"w":"עֹ֨שֶׁר","l":"6239","m":"HNcmsa","s":"H6239","t":"ʿšr"},{"i":8,"w":"וּ/נְכָסִ֜ים","l":"c/5233","m":"HC/Ncmpa","s":"H5233","t":"w/nksym"},{"i":9,"w":"וְ/הִשְׁלִיט֨/וֹ","l":"c/7980","m":"HC/Vhp3ms/Sp3ms","s":"H7980","t":"w/hšlyṭ/w"},{"i":10,"w":"לֶ/אֱכֹ֤ל","l":"l/398","m":"HR/Vqc","s":"H0398","t":"l/ʾkl"},{"i":11,"w":"מִמֶּ֨/נּוּ֙","l":"4480 a","m":"HR/Sp1cp","s":"H4480","t":"mm/nw"},{"i":12,"w":"וְ/לָ/שֵׂ֣את","l":"c/l/5375","m":"HC/R/Vqc","s":"H5375","t":"w/l/šʾt"},{"i":13,"w":"אֶת","l":"853","m":"HTo","s":"H0853","t":"ʾt"},{"i":14,"w":"חֶלְק֔/וֹ","l":"2506 a","m":"HNcmsc/Sp3ms","s":"H2506","t":"ḥlq/w"},{"i":15,"w":"וְ/לִ/שְׂמֹ֖חַ","l":"c/l/8055","m":"HC/R/Vqc","s":"H8055","t":"w/l/šmḥ"},{"i":16,"w":"בַּ/עֲמָל֑/וֹ","l":"b/5999","m":"HR/Ncbsc/Sp3ms","s":"H5999","t":"b/ʿml/w"},{"i":17,"w":"זֹ֕ה","l":"2090","m":"HPdxms","s":"H2090","t":"zh"},{"i":18,"w":"מַתַּ֥ת","l":"4991","m":"HNcfsc","s":"H4991","t":"mtt"},{"i":19,"w":"אֱלֹהִ֖ים","l":"430","m":"HNcmpa","s":"H0430","t":"ʾlhym"},{"i":20,"w":"הִֽיא","l":"1931","m":"HPp3fs","s":"H1931","t":"hyʾ"}],"gloss":{"H1571":"H1571 =","H3605":"H3605 =","H0120":"H0120H = a Spelling of","H5414":"H5414Q = a Meaning of","H0430":"H0430I = a Part of","H6239":"H6239 =","H5233":"H5233 =","H7980":"H7980 =","H0398":"H0398 =","H5375":"H5375X = a Meaning of","H0853":"H0853 =","H8055":"H8055 =","H5999":"H5999 =","H2090":"H2090 =","H4991":"H4991 =","H1931":"H1931 ="},"align_phrase":[]},{"v":19,"sq":"Çdo njeriu të cilit Perëndia i jep pasuri dhe të mira dhe të cilit i jep gjithashtu mundësinë t'i gëzojë ato, të marrë pjesën e vet dhe të gëzojë mundin e tij, kjo është një dhuratë e Perëndisë.","src":[{"i":0,"w":"כִּ֚י","l":"3588 a","m":"HC","s":"H3588","t":"ky"},{"i":1,"w":"לֹ֣א","l":"3808","m":"HTn","s":"H3808","t":"lʾ"},{"i":2,"w":"הַרְבֵּ֔ה","l":"7235 a","m":"HVha","s":"H7235","t":"hrbh"},{"i":3,"w":"יִזְכֹּ֖ר","l":"2142","m":"HVqi3ms","s":"H2142","t":"yzkr"},{"i":4,"w":"אֶת","l":"853","m":"HTo","s":"H0853","t":"ʾt"},{"i":5,"w":"יְמֵ֣י","l":"3117","m":"HNcmpc","s":"H3117","t":"ymy"},{"i":6,"w":"חַיָּ֑י/ו","l":"2416 e","m":"HNcmpc/Sp3ms","s":"H2416","t":"ḥyy/w"},{"i":7,"w":"כִּ֧י","l":"3588 a","m":"HC","s":"H3588","t":"ky"},{"i":8,"w":"הָ/אֱלֹהִ֛ים","l":"d/430","m":"HTd/Ncmpa","s":"H0430","t":"h/ʾlhym"},{"i":9,"w":"מַעֲנֶ֖ה","l":"6031 a","m":"HVhrmsa","s":"H6031","t":"mʿnh"},{"i":10,"w":"בְּ/שִׂמְחַ֥ת","l":"b/8057","m":"HR/Ncfsc","s":"H8057","t":"b/šmḥt"},{"i":11,"w":"לִבּֽ/וֹ","l":"3820 a","m":"HNcmsc/Sp3ms","s":"H3820","t":"lb/w"}],"gloss":{"H3808":"H3808 =","H2142":"H2142 =","H0853":"H0853 =","H3117":"H3117L = a Meaning of","H0430":"H0430I = a Part of","H8057":"H8057 ="},"align_phrase":[]}],"_meta":{"lang_src":"heb","lang_tgt":"sq","sources":{"text":"WLC (via OSHB)","morph":"OSHB morphology","gloss":"STEPBible TBESH (optional)"},"generated_at":"2025-10-15T03:21:47Z","license_notes":"See LICENSES.md"}}