{"ref":{"book":"Psalms (WLC)","book_sq":"Psalmet","chapter":74},"verses":[{"v":1,"sq":"O Perëndi, pse na ke hedhur poshtë për gjithnjë? Pse vlon zemërimi yt kundër kopesë së kullotës sate?","src":[{"i":0,"w":"מַשְׂכִּ֗יל","l":"4905","m":"HNcmsa","s":"H4905","t":"mškyl"},{"i":1,"w":"לְ/אָ֫סָ֥ף","l":"l/623","m":"HR/Np","s":"H0623","t":"l/ʾsp"},{"i":2,"w":"לָ/מָ֣ה","l":"l/4100","m":"HR/Ti","s":"H4100","t":"l/mh"},{"i":3,"w":"אֱ֭לֹהִים","l":"430","m":"HNcmpa","s":"H0430","t":"ʾlhym"},{"i":4,"w":"זָנַ֣חְתָּ","l":"2186 a","m":"HVqp2ms","s":"H2186","t":"znḥt"},{"i":5,"w":"לָ/נֶ֑צַח","l":"l/5331","m":"HR/Ncmsa","s":"H5331","t":"l/nṣḥ"},{"i":6,"w":"יֶעְשַׁ֥ן","l":"6225","m":"HVqi3ms","s":"H6225","t":"yʿšn"},{"i":7,"w":"אַ֝פְּ/ךָ֗","l":"639","m":"HNcmsc/Sp2ms","s":"H0639","t":"ʾp/k"},{"i":8,"w":"בְּ/צֹ֣אן","l":"b/6629","m":"HR/Ncbsc","s":"H6629","t":"b/ṣʾn"},{"i":9,"w":"מַרְעִיתֶֽ/ךָ","l":"4830","m":"HNcfsc/Sp2ms","s":"H4830","t":"mrʿyt/k"}],"gloss":{"H4905":"H4905 =","H0623":"H0623K = a Name of","H4100":"H4100 =","H0430":"H0430I = a Part of","H5331":"H5331 =","H6225":"H6225 =","H0639":"H0639I =","H6629":"H6629H =","H4830":"H4830 ="},"align_phrase":[]},{"v":2,"sq":"Kujto popullin tënd, që dikur e more, që ti e shpengove që të ishte fisi i trashëgimisë sate, të këtij mali të Sionit, mbi të cilin ke banuar.","src":[{"i":0,"w":"זְכֹ֤ר","l":"2142","m":"HVqv2ms","s":"H2142","t":"zkr"},{"i":1,"w":"עֲדָתְ/ךָ֨","l":"5712","m":"HNcfsc/Sp2ms","s":"H5712","t":"ʿdt/k"},{"i":2,"w":"קָ֘נִ֤יתָ","l":"7069","m":"HVqp2ms","s":"H7069","t":"qnyt"},{"i":3,"w":"קֶּ֗דֶם","l":"6924 a","m":"HNcmsa","s":"H6924","t":"qdm"},{"i":4,"w":"גָּ֭אַלְתָּ","l":"1350 a","m":"HVqp2ms","s":"H1350","t":"gʾlt"},{"i":5,"w":"שֵׁ֣בֶט","l":"7626","m":"HNcmsc","s":"H7626","t":"šbṭ"},{"i":6,"w":"נַחֲלָתֶ֑/ךָ","l":"5159","m":"HNcfsc/Sp2ms","s":"H5159","t":"nḥlt/k"},{"i":7,"w":"הַר","l":"2022","m":"HNcmsc","s":"H2022","t":"hr"},{"i":8,"w":"צִ֝יּ֗וֹן","l":"6726","m":"HNp","s":"H6726","t":"ṣywn"},{"i":9,"w":"זֶ֤ה","l":"2088","m":"HPdxms","s":"H2088","t":"zh"},{"i":10,"w":"שָׁכַ֬נְתָּ","l":"7931","m":"HVqp2ms","s":"H7931","t":"šknt"},{"i":11,"w":"בּֽ/וֹ","l":"b","m":"HR/Sp3ms","s":"","t":"b/w"}],"gloss":{"H2142":"H2142 =","H5712":"H5712 =","H7069":"H7069 =","H7626":"H7626J = a Meaning of","H5159":"H5159 =","H2022":"H2022H = a Meaning of","H6726":"H6726 = a Name of","H2088":"H2088 =","H7931":"H7931 ="},"align_phrase":[]},{"v":3,"sq":"Drejto hapat e tua në këto rrënoja të pandreqshme; armiku i ka prishur të gjitha në shenjtërore.","src":[{"i":0,"w":"הָרִ֣ימָ/ה","l":"7311 a","m":"HVhv2ms/Sh","s":"H7311","t":"hrym/h"},{"i":1,"w":"פְ֭עָמֶי/ךָ","l":"6471","m":"HNcfpc/Sp2ms","s":"H6471","t":"pʿmy/k"},{"i":2,"w":"לְ/מַשֻּׁא֣וֹת","l":"l/4876","m":"HR/Ncfpc","s":"H4876","t":"l/mšʾwt"},{"i":3,"w":"נֶ֑צַח","l":"5331","m":"HNcmsa","s":"H5331","t":"nṣḥ"},{"i":4,"w":"כָּל","l":"3605","m":"HNcmsc","s":"H3605","t":"kl"},{"i":5,"w":"הֵרַ֖ע","l":"7489 a","m":"HVhp3ms","s":"H7489","t":"hrʿ"},{"i":6,"w":"אוֹיֵ֣ב","l":"341","m":"HVqrmsa","s":"H0341","t":"ʾwyb"},{"i":7,"w":"בַּ/קֹּֽדֶשׁ","l":"b/6944","m":"HRd/Ncmsa","s":"H6944","t":"b/qdš"}],"gloss":{"H6471":"H6471 =","H4876":"H4876 =","H5331":"H5331 =","H3605":"H3605 =","H0341":"H0341 =","H6944":"H6944J ="},"align_phrase":[]},{"v":4,"sq":"Armiqtë e tu vrumbullojnë në vendin e kuvendeve të tua; kanë vënë aty shenjat e tyre si flamuj.","src":[{"i":0,"w":"שָׁאֲג֣וּ","l":"7580","m":"HVqp3cp","s":"H7580","t":"šʾgw"},{"i":1,"w":"צֹ֭רְרֶי/ךָ","l":"6887 d","m":"HVqrmpc/Sp2ms","s":"H6887","t":"ṣrry/k"},{"i":2,"w":"בְּ/קֶ֣רֶב","l":"b/7130","m":"HR/Ncmsc","s":"H7130","t":"b/qrb"},{"i":3,"w":"מוֹעֲדֶ֑/ךָ","l":"4150","m":"HNcmsc/Sp2ms","s":"H4150","t":"mwʿd/k"},{"i":4,"w":"שָׂ֖מוּ","l":"7760 a","m":"HVqp3cp","s":"H7760","t":"šmw"},{"i":5,"w":"אוֹתֹתָ֣/ם","l":"226","m":"HNcbpc/Sp3mp","s":"H0226","t":"ʾwtt/m"},{"i":6,"w":"אֹתֽוֹת","l":"226","m":"HNcbpa","s":"H0226","t":"ʾtwt"}],"gloss":{"H7580":"H7580 =","H7130":"H7130H = a Meaning of","H4150":"H4150J = a Meaning of","H0226":"H0226H = a Meaning of"},"align_phrase":[]},{"v":5,"sq":"Dukej sikur godisnin me sëpata në pjesën e dëndur të një pylli.","src":[{"i":0,"w":"יִ֭וָּדַע","l":"3045","m":"HVNi3ms","s":"H3045","t":"ywdʿ"},{"i":1,"w":"כְּ/מֵבִ֣יא","l":"k/935","m":"HR/Vhrmsa","s":"H0935","t":"k/mbyʾ"},{"i":2,"w":"לְ/מָ֑עְלָ/ה","l":"l/4605","m":"HR/D/Sd","s":"H4605","t":"l/mʿl/h"},{"i":3,"w":"בִּֽ/סֲבָךְ","l":"b/5442","m":"HR/Ncmsc","s":"H5442","t":"b/sbk"},{"i":4,"w":"עֵ֝֗ץ","l":"6086","m":"HNcmsa","s":"H6086","t":"ʿṣ"},{"i":5,"w":"קַרְדֻּמּֽוֹת","l":"7134","m":"HNcbpa","s":"H7134","t":"qrdmwt"}],"gloss":{"H3045":"H3045 =","H0935":"H0935P = a Meaning of","H4605":"H4605 =","H5442":"H5442 =","H6086":"H6086K = a Meaning of","H7134":"H7134 ="},"align_phrase":[]},{"v":6,"sq":"Dhe tani me sqeparë dhe çekane po prishin tërë skulpturat e tij.","src":[{"i":0,"w":"ו/עת","l":"c/6258","m":"HC/D","s":"H6258","t":"w/ʿt"},{"i":1,"w":"וְ֭/עַתָּה","l":"c/6258","m":"HC/D","s":"H6258","t":"w/ʿth"},{"i":2,"w":"פִּתּוּחֶ֣י/הָ","l":"6603","m":"HNcmpc/Sp3fs","s":"H6603","t":"ptwḥy/h"},{"i":3,"w":"יָּ֑חַד","l":"3162 a","m":"HD","s":"H3162","t":"yḥd"},{"i":4,"w":"בְּ/כַשִּׁ֥יל","l":"b/3781","m":"HR/Ncmsa","s":"H3781","t":"b/kšyl"},{"i":5,"w":"וְ֝/כֵֽילַפֹּ֗ת","l":"c/3597","m":"HC/Ncfpa","s":"H3597","t":"w/kylpt"},{"i":6,"w":"יַהֲלֹמֽוּ/ן","l":"1986","m":"HVqi3mp/Sn","s":"H1986","t":"yhlmw/n"}],"gloss":{"H6258":"H6258 =","H6603":"H6603 =","H3781":"H3781 =","H3597":"H3597 =","H1986":"H1986 ="},"align_phrase":[]},{"v":7,"sq":"I kanë vënë zjarrin shenjtërores sate; kanë përdhosur banesën që mban emrin tënd, duke e hedhur poshtë.","src":[{"i":0,"w":"שִׁלְח֣וּ","l":"7971","m":"HVpp3cp","s":"H7971","t":"šlḥw"},{"i":1,"w":"בָ֭/אֵשׁ","l":"b/784","m":"HRd/Ncbsa","s":"H0784","t":"b/ʾš"},{"i":2,"w":"מִקְדָּשֶׁ֑/ךָ","l":"4720","m":"HNcmsc/Sp2ms","s":"H4720","t":"mqdš/k"},{"i":3,"w":"לָ֝/אָ֗רֶץ","l":"l/776","m":"HRd/Ncbsa","s":"H0776","t":"l/ʾrṣ"},{"i":4,"w":"חִלְּל֥וּ","l":"2490 c","m":"HVpp3cp","s":"H2490","t":"ḥllw"},{"i":5,"w":"מִֽשְׁכַּן","l":"4908","m":"HNcmsc","s":"H4908","t":"mškn"},{"i":6,"w":"שְׁמֶֽ/ךָ","l":"8034","m":"HNcmsc/Sp2ms","s":"H8034","t":"šm/k"}],"gloss":{"H7971":"H7971M = a Meaning of","H0784":"H0784 =","H4720":"H4720 =","H0776":"H0776H =","H4908":"H4908 =","H8034":"H8034 ="},"align_phrase":[]},{"v":8,"sq":"Kanë thënë në zemër të tyre: \\\"T'i shkatërrojmë të gjithë\\\"; kanë djegur tërë qendrat e kuvendeve të shenjta në vend.","src":[{"i":0,"w":"אָמְר֣וּ","l":"559","m":"HVqp3cp","s":"H0559","t":"ʾmrw"},{"i":1,"w":"בְ֭/לִבָּ/ם","l":"b/3820 a","m":"HR/Ncmsc/Sp3mp","s":"H3820","t":"b/lb/m"},{"i":2,"w":"נִינָ֣/ם","l":"3238","m":"HNcmsc/Sp3mp","s":"H3238","t":"nyn/m"},{"i":3,"w":"יָ֑חַד","l":"3162 a","m":"HNcmsa","s":"H3162","t":"yḥd"},{"i":4,"w":"שָׂרְפ֖וּ","l":"8313","m":"HVqp3cp","s":"H8313","t":"šrpw"},{"i":5,"w":"כָל","l":"3605","m":"HNcmsc","s":"H3605","t":"kl"},{"i":6,"w":"מוֹעֲדֵי","l":"4150","m":"HNcmpc","s":"H4150","t":"mwʿdy"},{"i":7,"w":"אֵ֣ל","l":"410","m":"HNcmsa","s":"H0410","t":"ʾl"},{"i":8,"w":"בָּ/אָֽרֶץ","l":"b/776","m":"HRd/Ncbsa","s":"H0776","t":"b/ʾrṣ"}],"gloss":{"H0559":"H0559 =","H3238":"H3238 =","H8313":"H8313 =","H3605":"H3605 =","H4150":"H4150J = a Meaning of","H0410":"H0410L = a Meaning of","H0776":"H0776H ="},"align_phrase":[]},{"v":9,"sq":"Ne nuk i shohim më shenjat tona; nuk ka më profet dhe midis nesh nuk ka asnjë që të dijë deri kur.","src":[{"i":0,"w":"אֽוֹתֹתֵ֗י/נוּ","l":"226","m":"HNcbpc/Sp1cp","s":"H0226","t":"ʾwtty/nw"},{"i":1,"w":"לֹ֥א","l":"3808","m":"HTn","s":"H3808","t":"lʾ"},{"i":2,"w":"רָ֫אִ֥ינוּ","l":"7200","m":"HVqp1cp","s":"H7200","t":"rʾynw"},{"i":3,"w":"אֵֽין","l":"369","m":"HTn","s":"H0369","t":"ʾyn"},{"i":4,"w":"ע֥וֹד","l":"5750","m":"HD","s":"H5750","t":"ʿwd"},{"i":5,"w":"נָבִ֑יא","l":"5030","m":"HNcmsa","s":"H5030","t":"nbyʾ"},{"i":6,"w":"וְ/לֹֽא","l":"c/3808","m":"HC/Tn","s":"H3808","t":"w/lʾ"},{"i":7,"w":"אִ֝תָּ֗/נוּ","l":"854","m":"HR/Sp1cp","s":"H0854","t":"ʾt/nw"},{"i":8,"w":"יֹדֵ֥עַ","l":"3045","m":"HVqrmsa","s":"H3045","t":"ydʿ"},{"i":9,"w":"עַד","l":"5704","m":"HR","s":"H5704","t":"ʿd"},{"i":10,"w":"מָֽה","l":"4100","m":"HTi","s":"H4100","t":"mh"}],"gloss":{"H0226":"H0226H = a Meaning of","H3808":"H3808 =","H7200":"H7200N = a Name of","H0369":"H0369 =","H5750":"H5750 =","H5030":"H5030 =","H0854":"H0854 =","H3045":"H3045 =","H5704":"H5704 =","H4100":"H4100 ="},"align_phrase":[]},{"v":10,"sq":"Deri kur, o Perëndi, kundërshtari do të fyejë? Armiku vallë, do ta përçmojë emrin tënd përjetë?","src":[{"i":0,"w":"עַד","l":"5704","m":"HR","s":"H5704","t":"ʿd"},{"i":1,"w":"מָתַ֣י","l":"4970","m":"HTi","s":"H4970","t":"mty"},{"i":2,"w":"אֱ֭לֹהִים","l":"430","m":"HNcmpa","s":"H0430","t":"ʾlhym"},{"i":3,"w":"יְחָ֣רֶף","l":"2778 a","m":"HVpi3ms","s":"H2778","t":"yḥrp"},{"i":4,"w":"צָ֑ר","l":"6862 c","m":"HNcmsa","s":"H6862","t":"ṣr"},{"i":5,"w":"יְנָ֘אֵ֤ץ","l":"5006","m":"HVpi3ms","s":"H5006","t":"ynʾṣ"},{"i":6,"w":"אוֹיֵ֖ב","l":"341","m":"HVqrmsa","s":"H0341","t":"ʾwyb"},{"i":7,"w":"שִׁמְ/ךָ֣","l":"8034","m":"HNcmsc/Sp2ms","s":"H8034","t":"šm/k"},{"i":8,"w":"לָ/נֶֽצַח","l":"l/5331","m":"HR/Ncmsa","s":"H5331","t":"l/nṣḥ"}],"gloss":{"H5704":"H5704 =","H4970":"H4970 =","H0430":"H0430I = a Part of","H5006":"H5006 =","H0341":"H0341 =","H8034":"H8034 =","H5331":"H5331 ="},"align_phrase":[]},{"v":11,"sq":"Pse e tërheq dorën tënde, pikërisht të djathtën? Nxirre nga gjiri yt dhe shkatërroji.","src":[{"i":0,"w":"לָ֤/מָּה","l":"l/4100","m":"HR/Ti","s":"H4100","t":"l/mh"},{"i":1,"w":"תָשִׁ֣יב","l":"7725","m":"HVhi2ms","s":"H7725","t":"tšyb"},{"i":2,"w":"יָ֭דְ/ךָ","l":"3027","m":"HNcbsc/Sp2ms","s":"H3027","t":"yd/k"},{"i":3,"w":"וִֽ/ימִינֶ֑/ךָ","l":"c/3225","m":"HC/Ncfsc/Sp2ms","s":"H3225","t":"w/ymyn/k"},{"i":4,"w":"מִ/קֶּ֖רֶב","l":"m/7130","m":"HR/Ncmsc","s":"H7130","t":"m/qrb"},{"i":5,"w":"חוק/ך","l":"2706","m":"HNcmsc/Sp2ms","s":"H2706","t":"ḥwq/k"},{"i":6,"w":"חֵֽיקְ/ךָ֣","l":"2436","m":"HNcmsc/Sp2ms","s":"H2436","t":"ḥyq/k"},{"i":7,"w":"כַלֵּֽה","l":"3615","m":"HVpv2ms","s":"H3615","t":"klh"}],"gloss":{"H4100":"H4100 =","H7725":"H7725O = a Meaning of","H3027":"H3027X = a Meaning of","H3225":"H3225I = a Name of","H7130":"H7130H = a Meaning of","H2706":"H2706I = a Meaning of","H2436":"H2436J = a Meaning of","H3615":"H3615J = a Meaning of"},"align_phrase":[]},{"v":12,"sq":"Por Perëndia është mbreti im qysh prej kohëve të lashta; ai sjell shpëtimin mbi tokë.","src":[{"i":0,"w":"וֵ֭/אלֹהִים","l":"c/430","m":"HC/Ncmpa","s":"H0430","t":"w/ʾlhym"},{"i":1,"w":"מַלְכִּ֣/י","l":"4428","m":"HNcmsc/Sp1cs","s":"H4428","t":"mlk/y"},{"i":2,"w":"מִ/קֶּ֑דֶם","l":"m/6924 a","m":"HR/Ncmsa","s":"H6924","t":"m/qdm"},{"i":3,"w":"פֹּעֵ֥ל","l":"6466","m":"HVqrmsa","s":"H6466","t":"pʿl"},{"i":4,"w":"יְ֝שׁוּע֗וֹת","l":"3444","m":"HNcfpa","s":"H3444","t":"yšwʿwt"},{"i":5,"w":"בְּ/קֶ֣רֶב","l":"b/7130","m":"HR/Ncmsc","s":"H7130","t":"b/qrb"},{"i":6,"w":"הָ/אָֽרֶץ","l":"d/776","m":"HTd/Ncbsa","s":"H0776","t":"h/ʾrṣ"}],"gloss":{"H0430":"H0430I = a Part of","H4428":"H4428L =","H6466":"H6466 =","H3444":"H3444 =","H7130":"H7130H = a Meaning of","H0776":"H0776H ="},"align_phrase":[]},{"v":13,"sq":"Me forcën tënde ndave detin dhe shtype kokën e përbindëshve të detit në ujërat.","src":[{"i":0,"w":"אַתָּ֤ה","l":"859 a","m":"HPp2ms","s":"H0859","t":"ʾth"},{"i":1,"w":"פוֹרַ֣רְתָּ","l":"6565 b","m":"HVmp2ms","s":"H6565","t":"pwrrt"},{"i":2,"w":"בְ/עָזְּ/ךָ֣","l":"b/5797","m":"HR/Ncmsc/Sp2ms","s":"H5797","t":"b/ʿz/k"},{"i":3,"w":"יָ֑ם","l":"3220","m":"HNcmsa","s":"H3220","t":"ym"},{"i":4,"w":"שִׁבַּ֖רְתָּ","l":"7665","m":"HVpp2ms","s":"H7665","t":"šbrt"},{"i":5,"w":"רָאשֵׁ֥י","l":"7218 a","m":"HNcmpc","s":"H7218","t":"rʾšy"},{"i":6,"w":"תַ֝נִּינִ֗ים","l":"8577 b","m":"HNcmpa","s":"H8577","t":"tnynym"},{"i":7,"w":"עַל","l":"5921 a","m":"HR","s":"H5921","t":"ʿl"},{"i":8,"w":"הַ/מָּֽיִם","l":"d/4325","m":"HTd/Ncmpa","s":"H4325","t":"h/mym"}],"gloss":{"H5797":"H5797 =","H3220":"H3220I = a Name of","H7665":"H7665 =","H4325":"H4325H ="},"align_phrase":[]},{"v":14,"sq":"Copëtove kokat e Levitanëve dhe ia dhe për të ngrënë popullit të shkretëtirës.","src":[{"i":0,"w":"אַתָּ֣ה","l":"859 a","m":"HPp2ms","s":"H0859","t":"ʾth"},{"i":1,"w":"רִ֭צַּצְתָּ","l":"7533","m":"HVpp2ms","s":"H7533","t":"rṣṣt"},{"i":2,"w":"רָאשֵׁ֣י","l":"7218 a","m":"HNcmpc","s":"H7218","t":"rʾšy"},{"i":3,"w":"לִוְיָתָ֑ן","l":"3882","m":"HNcmsa","s":"H3882","t":"lwytn"},{"i":4,"w":"תִּתְּנֶ֥/נּוּ","l":"5414","m":"HVqi2ms/Sp3ms","s":"H5414","t":"ttn/nw"},{"i":5,"w":"מַ֝אֲכָ֗ל","l":"3978","m":"HNcmsa","s":"H3978","t":"mʾkl"},{"i":6,"w":"לְ/עָ֣ם","l":"l/5971 a","m":"HR/Ncmsa","s":"H5971","t":"l/ʿm"},{"i":7,"w":"לְ/צִיִּֽים","l":"l/6728","m":"HR/Ncmpa","s":"H6728","t":"l/ṣyym"}],"gloss":{"H7533":"H7533 =","H3882":"H3882 =","H5414":"H5414Q = a Meaning of","H3978":"H3978 =","H6728":"H6728 ="},"align_phrase":[]},{"v":15,"sq":"Bëre që të dalin burime dhe përrenj dhe thave lumenj të përhershëm.","src":[{"i":0,"w":"אַתָּ֣ה","l":"859 a","m":"HPp2ms","s":"H0859","t":"ʾth"},{"i":1,"w":"בָ֭קַעְתָּ","l":"1234","m":"HVqp2ms","s":"H1234","t":"bqʿt"},{"i":2,"w":"מַעְיָ֣ן","l":"4599","m":"HNcmsa","s":"H4599","t":"mʿyn"},{"i":3,"w":"וָ/נָ֑חַל","l":"c/5158 a","m":"HC/Ncmsa","s":"H5158","t":"w/nḥl"},{"i":4,"w":"אַתָּ֥ה","l":"859 a","m":"HPp2ms","s":"H0859","t":"ʾth"},{"i":5,"w":"ה֝וֹבַ֗שְׁתָּ","l":"3001","m":"HVhp2ms","s":"H3001","t":"hwbšt"},{"i":6,"w":"נַהֲר֥וֹת","l":"5104","m":"HNcmpc","s":"H5104","t":"nhrwt"},{"i":7,"w":"אֵיתָֽן","l":"386","m":"HAamsa","s":"H0386","t":"ʾytn"}],"gloss":{"H1234":"H1234 =","H4599":"H4599 =","H3001":"H3001 =","H5104":"H5104H =","H0386":"H0386 ="},"align_phrase":[]},{"v":16,"sq":"Jotja është dita, jotja është edhe nata; ti ke vendosur dritën dhe diellin.","src":[{"i":0,"w":"לְ/ךָ֣","l":"l","m":"HR/Sp2ms","s":"","t":"l/k"},{"i":1,"w":"י֭וֹם","l":"3117","m":"HNcmsa","s":"H3117","t":"ywm"},{"i":2,"w":"אַף","l":"637","m":"HTa","s":"H0637","t":"ʾp"},{"i":3,"w":"לְ/ךָ֥","l":"l","m":"HR/Sp2ms","s":"","t":"l/k"},{"i":4,"w":"לָ֑יְלָה","l":"3915","m":"HNcmsa","s":"H3915","t":"lylh"},{"i":5,"w":"אַתָּ֥ה","l":"859 a","m":"HPp2ms","s":"H0859","t":"ʾth"},{"i":6,"w":"הֲ֝כִינ֗וֹתָ","l":"3559 a","m":"HVhp2ms","s":"H3559","t":"hkynwt"},{"i":7,"w":"מָא֥וֹר","l":"3974","m":"HNcmsa","s":"H3974","t":"mʾwr"},{"i":8,"w":"וָ/שָֽׁמֶשׁ","l":"c/8121","m":"HC/Ncbsa","s":"H8121","t":"w/šmš"}],"gloss":{"H3117":"H3117L = a Meaning of","H0637":"H0637 =","H3915":"H3915 =","H3974":"H3974 =","H8121":"H8121 ="},"align_phrase":[]},{"v":17,"sq":"Ti ke caktuar tërë kufijtë e tokës dhe ke bërë verën dhe dimrin.","src":[{"i":0,"w":"אַתָּ֣ה","l":"859 a","m":"HPp2ms","s":"H0859","t":"ʾth"},{"i":1,"w":"הִ֭צַּבְתָּ","l":"5324","m":"HVhp2ms","s":"H5324","t":"hṣbt"},{"i":2,"w":"כָּל","l":"3605","m":"HNcmsc","s":"H3605","t":"kl"},{"i":3,"w":"גְּבוּל֣וֹת","l":"1367","m":"HNcfpc","s":"H1367","t":"gbwlwt"},{"i":4,"w":"אָ֑רֶץ","l":"776","m":"HNcbsa","s":"H0776","t":"ʾrṣ"},{"i":5,"w":"קַ֥יִץ","l":"7019","m":"HNcmsa","s":"H7019","t":"qyṣ"},{"i":6,"w":"וָ֝/חֹ֗רֶף","l":"c/2779","m":"HC/Ncmsa","s":"H2779","t":"w/ḥrp"},{"i":7,"w":"אַתָּ֥ה","l":"859 a","m":"HPp2ms","s":"H0859","t":"ʾth"},{"i":8,"w":"יְצַרְתָּ/ם","l":"3335","m":"HVqp2ms/Sp3mp","s":"H3335","t":"yṣrt/m"}],"gloss":{"H5324":"H5324 =","H3605":"H3605 =","H1367":"H1367 =","H0776":"H0776H =","H7019":"H7019 =","H2779":"H2779 =","H3335":"H3335I = a Meaning of"},"align_phrase":[]},{"v":18,"sq":"Mbaje mend këtë, o Zot, që armiku të ka fyer dhe që një popull i pamend ka përbuzur emrin tënd.","src":[{"i":0,"w":"זְכָר","l":"2142","m":"HVqv2ms","s":"H2142","t":"zkr"},{"i":1,"w":"זֹ֗את","l":"2063","m":"HPdxfs","s":"H2063","t":"zʾt"},{"i":2,"w":"א֭וֹיֵב","l":"341","m":"HVqrmsa","s":"H0341","t":"ʾwyb"},{"i":3,"w":"חֵרֵ֣ף","l":"2778 a","m":"HVpp3ms","s":"H2778","t":"ḥrp"},{"i":4,"w":"יְהוָ֑ה","l":"3068","m":"HNp","s":"H3068","t":"yhwh"},{"i":5,"w":"וְ/עַ֥ם","l":"c/5971 a","m":"HC/Ncmsa","s":"H5971","t":"w/ʿm"},{"i":6,"w":"נָ֝בָ֗ל","l":"5036","m":"HAamsa","s":"H5036","t":"nbl"},{"i":7,"w":"נִֽאֲצ֥וּ","l":"5006","m":"HVpp3cp","s":"H5006","t":"nʾṣw"},{"i":8,"w":"שְׁמֶֽ/ךָ","l":"8034","m":"HNcmsc/Sp2ms","s":"H8034","t":"šm/k"}],"gloss":{"H2142":"H2142 =","H2063":"H2063 =","H0341":"H0341 =","H3068":"H3068I = a Part of","H5036":"H5036 =","H5006":"H5006 =","H8034":"H8034 ="},"align_phrase":[]},{"v":19,"sq":"Mos ia braktis bishave jetën e turtulleshës sate; mos harro përjetë jetën e të përvuajturve të tu.","src":[{"i":0,"w":"אַל","l":"408","m":"HTn","s":"H0408","t":"ʾl"},{"i":1,"w":"תִּתֵּ֣ן","l":"5414","m":"HVqj2ms","s":"H5414","t":"ttn"},{"i":2,"w":"לְ֭/חַיַּת","l":"l/2416 c","m":"HR/Ncfsc","s":"H2416","t":"l/ḥyt"},{"i":3,"w":"נֶ֣פֶשׁ","l":"5315","m":"HNcbsc","s":"H5315","t":"npš"},{"i":4,"w":"תּוֹרֶ֑/ךָ","l":"8449","m":"HNcbsc/Sp2ms","s":"H8449","t":"twr/k"},{"i":5,"w":"חַיַּ֥ת","l":"2416 d","m":"HNcfsc","s":"H2416","t":"ḥyt"},{"i":6,"w":"עֲ֝נִיֶּ֗י/ךָ","l":"6041","m":"HAampc/Sp2ms","s":"H6041","t":"ʿnyy/k"},{"i":7,"w":"אַל","l":"408","m":"HTn","s":"H0408","t":"ʾl"},{"i":8,"w":"תִּשְׁכַּ֥ח","l":"7911","m":"HVqj2ms","s":"H7911","t":"tškḥ"},{"i":9,"w":"לָ/נֶֽצַח","l":"l/5331","m":"HR/Ncmsa","s":"H5331","t":"l/nṣḥ"}],"gloss":{"H0408":"H0408 =","H5414":"H5414Q = a Meaning of","H5315":"H5315N = a Meaning of","H8449":"H8449 =","H6041":"H6041 =","H7911":"H7911 =","H5331":"H5331 ="},"align_phrase":[]},{"v":20,"sq":"Respekto besëlidhjen, sepse vendet e errëta të tokës janë plot me strofka dhune.","src":[{"i":0,"w":"הַבֵּ֥ט","l":"5027","m":"HVhv2ms","s":"H5027","t":"hbṭ"},{"i":1,"w":"לַ/בְּרִ֑ית","l":"l/1285","m":"HRd/Ncfsa","s":"H1285","t":"l/bryt"},{"i":2,"w":"כִּ֥י","l":"3588 a","m":"HC","s":"H3588","t":"ky"},{"i":3,"w":"מָלְא֥וּ","l":"4390","m":"HVqp3cp","s":"H4390","t":"mlʾw"},{"i":4,"w":"מַחֲשַׁכֵּי","l":"4285","m":"HNcmpc","s":"H4285","t":"mḥšky"},{"i":5,"w":"אֶ֝֗רֶץ","l":"776","m":"HNcbsa","s":"H0776","t":"ʾrṣ"},{"i":6,"w":"נְא֣וֹת","l":"4999","m":"HNcfpc","s":"H4999","t":"nʾwt"},{"i":7,"w":"חָמָֽס","l":"2555","m":"HNcmsa","s":"H2555","t":"ḥms"}],"gloss":{"H5027":"H5027 =","H1285":"H1285 =","H4390":"H4390 =","H4285":"H4285 =","H0776":"H0776H =","H4999":"H4999 =","H2555":"H2555 ="},"align_phrase":[]},{"v":21,"sq":"Mos lejo që i shtypuri të kthehet i turpëruar; bëj që i përvuajturi dhe nevojtari të lëvdojnë emrin tënd.","src":[{"i":0,"w":"אַל","l":"408","m":"HTn","s":"H0408","t":"ʾl"},{"i":1,"w":"יָשֹׁ֣ב","l":"7725","m":"HVqj3ms","s":"H7725","t":"yšb"},{"i":2,"w":"דַּ֣ךְ","l":"1790","m":"HAamsa","s":"H1790","t":"dk"},{"i":3,"w":"נִכְלָ֑ם","l":"3637","m":"HVNrmsa","s":"H3637","t":"nklm"},{"i":4,"w":"עָנִ֥י","l":"6041","m":"HAamsa","s":"H6041","t":"ʿny"},{"i":5,"w":"וְ֝/אֶבְי֗וֹן","l":"c/34","m":"HC/Aamsa","s":"H0034","t":"w/ʾbywn"},{"i":6,"w":"יְֽהַלְל֥וּ","l":"1984 b","m":"HVpi3mp","s":"H1984","t":"yhllw"},{"i":7,"w":"שְׁמֶֽ/ךָ","l":"8034","m":"HNcmsc/Sp2ms","s":"H8034","t":"šm/k"}],"gloss":{"H0408":"H0408 =","H7725":"H7725O = a Meaning of","H1790":"H1790 =","H3637":"H3637 =","H6041":"H6041 =","H0034":"H0034 =","H8034":"H8034 ="},"align_phrase":[]},{"v":22,"sq":"Çohu o Perëndi, mbro kauzën tënde! Mos harro që i pamendi të fyen tërë ditën.","src":[{"i":0,"w":"קוּמָ֣/ה","l":"6965 b","m":"HVqv2ms/Sh","s":"H6965","t":"qwm/h"},{"i":1,"w":"אֱ֭לֹהִים","l":"430","m":"HNcmpa","s":"H0430","t":"ʾlhym"},{"i":2,"w":"רִיבָ֣/ה","l":"7378","m":"HVqv2ms/Sh","s":"H7378","t":"ryb/h"},{"i":3,"w":"רִיבֶ֑/ךָ","l":"7379","m":"HNcbsc/Sp2ms","s":"H7379","t":"ryb/k"},{"i":4,"w":"זְכֹ֥ר","l":"2142","m":"HVqv2ms","s":"H2142","t":"zkr"},{"i":5,"w":"חֶרְפָּתְ/ךָ֥","l":"2781","m":"HNcfsc/Sp2ms","s":"H2781","t":"ḥrpt/k"},{"i":6,"w":"מִנִּי","l":"4480 a","m":"HR","s":"H4480","t":"mny"},{"i":7,"w":"נָ֝בָ֗ל","l":"5036","m":"HAamsa","s":"H5036","t":"nbl"},{"i":8,"w":"כָּל","l":"3605","m":"HNcmsc","s":"H3605","t":"kl"},{"i":9,"w":"הַ/יּֽוֹם","l":"d/3117","m":"HTd/Ncmsa","s":"H3117","t":"h/ywm"}],"gloss":{"H0430":"H0430I = a Part of","H7378":"H7378 =","H7379":"H7379 =","H2142":"H2142 =","H2781":"H2781 =","H5036":"H5036 =","H3605":"H3605 =","H3117":"H3117L = a Meaning of"},"align_phrase":[]},{"v":23,"sq":"Mos harro britmën e armiqve të tu; zhurma e tyre që ngrihen kundër teje ngjitet vazhdimisht në qiell.","src":[{"i":0,"w":"אַל","l":"408","m":"HTn","s":"H0408","t":"ʾl"},{"i":1,"w":"תִּ֭שְׁכַּח","l":"7911","m":"HVqj2ms","s":"H7911","t":"tškḥ"},{"i":2,"w":"ק֣וֹל","l":"6963 a","m":"HNcmsc","s":"H6963","t":"qwl"},{"i":3,"w":"צֹרְרֶ֑י/ךָ","l":"6887 d","m":"HVqrmpc/Sp2ms","s":"H6887","t":"ṣrry/k"},{"i":4,"w":"שְׁא֥וֹן","l":"7588","m":"HNcmsc","s":"H7588","t":"šʾwn"},{"i":5,"w":"קָ֝מֶ֗י/ךָ","l":"6965 b","m":"HVqrmpc/Sp2ms","s":"H6965","t":"qmy/k"},{"i":6,"w":"עֹלֶ֥ה","l":"5927","m":"HVqrmsa","s":"H5927","t":"ʿlh"},{"i":7,"w":"תָמִֽיד","l":"8548","m":"HNcmsa","s":"H8548","t":"tmyd"}],"gloss":{"H0408":"H0408 =","H7911":"H7911 =","H7588":"H7588 =","H5927":"H5927M = a Meaning of","H8548":"H8548 ="},"align_phrase":[]}],"_meta":{"lang_src":"heb","lang_tgt":"sq","sources":{"text":"WLC (via OSHB)","morph":"OSHB morphology","gloss":"STEPBible TBESH (optional)"},"generated_at":"2025-10-15T03:21:31Z","license_notes":"See LICENSES.md"}}